pivotnacci-0.0.2.data/scripts/pivotnacci
pivotnaccilib/__init__.py
pivotnaccilib/server.py
pivotnaccilib/agent/__init__.py
pivotnaccilib/agent/constants.py
pivotnaccilib/agent/error.py
pivotnaccilib/agent/session.py
pivotnaccilib/agent/structs.py
pivotnaccilib/agent/broker/__init__.py
pivotnaccilib/agent/broker/aspx.py
pivotnaccilib/agent/broker/base.py
pivotnaccilib/agent/broker/factory.py
pivotnaccilib/agent/broker/interface.py
pivotnaccilib/agent/broker/jsp.py
pivotnaccilib/agent/broker/php.py
pivotnaccilib/socks/__init__.py
pivotnaccilib/socks/error.py
pivotnaccilib/socks/initial_request.py
pivotnaccilib/socks/negotiator.py
pivotnaccilib/socks/socks4.py
pivotnaccilib/socks/socks5.py
pivotnacci-0.0.2.dist-info/LICENSE
pivotnacci-0.0.2.dist-info/METADATA
pivotnacci-0.0.2.dist-info/WHEEL
pivotnacci-0.0.2.dist-info/top_level.txt
pivotnacci-0.0.2.dist-info/RECORD
