Metadata-Version: 2.1
Name: pivotnacci
Version: 0.0.2
Summary: A tool to make socks connections through HTTP agents
Home-page: https://github.com/blackarrowsec/pivotnacci
Author: Eloy Perez
Author-email: eloy.perez@tarlogic.com
License: UNKNOWN
Platform: UNKNOWN
Classifier: Programming Language :: Python :: 3
Classifier: License :: OSI Approved :: GNU Affero General Public License v3
Classifier: Operating System :: OS Independent
Requires-Dist: construct
Requires-Dist: requests
